pipesche/__init__.py
pipesche/core/__init__.py
pipesche/core/datastore/__init__.py
pipesche/core/datastore/base.py
pipesche/core/datastore/in_memory.py
pipesche/core/node/__init__.py
pipesche/core/node/base.py
pipesche/core/pipeline/__init__.py
pipesche/core/pipeline/pipeline.py
pipesche/datastore/__init__.py
pipesche-0.1.8.dist-info/LICENSE
pipesche-0.1.8.dist-info/METADATA
pipesche-0.1.8.dist-info/WHEEL
pipesche-0.1.8.dist-info/RECORD
