Metadata-Version: 2.1
Name: pipesche
Version: 0.1.8
Summary: Using a defined data schema to pass data between nodes in the pipeli.
License: MIT
Author: Yoshi Gao
Author-email: yoshi4868686@gmail.com
Requires-Python: >=3.9,<4.0
Classifier: License :: OSI Approved :: MIT License
Classifier: Programming Language :: Python :: 3
Classifier: Programming Language :: Python :: 3.9
Classifier: Programming Language :: Python :: 3.10
Classifier: Programming Language :: Python :: 3.11
Classifier: Programming Language :: Python :: 3.12
Requires-Dist: networkx (>=3.2.1,<4.0.0)
